Metadata-Version: 2.1
Name: voicefixer
Version: 0.1.3
Summary: This package is written for the restoration of degraded speech
Home-page: https://github.com/haoheliu/voicefixer
Author: Haohe Liu
Author-email: haoheliu@gmail.com
License: MIT
Classifier: License :: OSI Approved :: MIT License
Classifier: Programming Language :: Python
Classifier: Programming Language :: Python :: 3
Classifier: Programming Language :: Python :: 3.7
Classifier: Programming Language :: Python :: Implementation :: CPython
Classifier: Programming Language :: Python :: Implementation :: PyPy
Requires-Python: >=3.7.0
License-File: LICENSE
Requires-Dist: librosa
Requires-Dist: matplotlib
Requires-Dist: torch (>=1.7.0)
Requires-Dist: progressbar
Requires-Dist: torchlibrosa
Requires-Dist: GitPython
Requires-Dist: streamlit (>=1.12.0)
Requires-Dist: pyyaml
